adadmire/__init__.py
adadmire/apgpy.py
adadmire/main.py
adadmire/mgm.py
adadmire-1.0.14.dist-info/METADATA
adadmire-1.0.14.dist-info/WHEEL
adadmire-1.0.14.dist-info/licenses/LICENSE
adadmire-1.0.14.dist-info/RECORD
