Metadata-Version: 2.1
Name: adadmire
Version: 1.0.14
Summary: Functions for detecting anomalies in tabular datasets using Mixed Graphical Models.
Project-URL: Homepage, https://github.com/spang-lab/adadmire
Project-URL: Bug Tracker, https://github.com/spang-lab/adadmire/issues
Author-email: Lena Buck <lena.buck@ukr.de>, Tobias Schmidt <tobias2.schmidt@ukr.de>
License-File: LICENSE
Classifier: License :: OSI Approved :: MIT License
Classifier: Operating System :: OS Independent
Classifier: Programming Language :: Python :: 3
Requires-Python: >=3.7
Requires-Dist: scikit-learn<2,>=1
Requires-Dist: scipy<2,>=1
